validate_uuid.py
validate_uuid-0.1.0.dist-info/METADATA
validate_uuid-0.1.0.dist-info/WHEEL
validate_uuid-0.1.0.dist-info/RECORD
