Metadata-Version: 2.1
Name: validate_uuid
Version: 0.1.0
Summary: Проверка УИд на валидность
Author: t1bon
Author-email: tim.batrudinov@gmail.com
Requires-Python: >=3.10,<4.0
Classifier: Programming Language :: Python :: 3
Classifier: Programming Language :: Python :: 3.10
Classifier: Programming Language :: Python :: 3.11
Classifier: Programming Language :: Python :: 3.12
